wrap_technote/__init__.py
wrap_technote/charts.py
wrap_technote/charts_rf.py
wrap_technote/charts_tds.py
wrap_technote/charts_utils.py
wrap_technote/charts_wl.py
wrap_technote/decimal_word.csv
wrap_technote/fileio.py
wrap_technote/gwutils.py
wrap_technote/rainfall.py
wrap_technote/reporting.py
wrap_technote/salinity.py
wrap_technote/utils.py
wrap_technote/waterlevels.py
wrap_technote/scripts/__init__.py
wrap_technote/scripts/cli.py
wrap_technote/scripts/rainfall.py
wrap_technote/scripts/salinities.py
wrap_technote/scripts/summaries.py
wrap_technote/scripts/waterlevels.py
wrap_technote/templates/static/bootstrap_base.html
wrap_technote/templates/static/gw_summary.html
wrap_technote/templates/static/rainfall.html
wrap_technote/templates/static/salinities.html
wrap_technote/templates/static/style.css
wrap_technote/templates/static/waterlevels.html
wrap_technote/templates/static/salinity/index.html
wrap_technote/templates/static_new_clean/index.html
wrap_technote-0.117.dist-info/LICENSE
wrap_technote-0.117.dist-info/METADATA
wrap_technote-0.117.dist-info/WHEEL
wrap_technote-0.117.dist-info/entry_points.txt
wrap_technote-0.117.dist-info/top_level.txt
wrap_technote-0.117.dist-info/RECORD
