Metadata-Version: 2.1
Name: wrap_technote
Version: 0.117
Summary: Code for the annual WRAP technical notes
Home-page: https://github.com/dew-waterscience/wrap_technote
Author: DEW Water Science (Kent Inverarity)
Author-email: kent.inverarity@sa.gov.au
License: All rights reserved @ DEW
Keywords: science groundwater
Classifier: Programming Language :: Python :: 3
Classifier: Topic :: Scientific/Engineering
License-File: LICENSE
Requires-Dist: loguru
Requires-Dist: matplotlib
Requires-Dist: shapely
Requires-Dist: pyshp
Requires-Dist: jinja2
Requires-Dist: click
Requires-Dist: requests
Requires-Dist: python-sa-gwdata >=0.5.4
Requires-Dist: adjustText
Requires-Dist: xlrd
Requires-Dist: openpyxl
Requires-Dist: pillow
Requires-Dist: pyproj
Requires-Dist: geopandas >=0.5.0
Requires-Dist: scipy
Requires-Dist: attrdict
Requires-Dist: ausweather >=0.90
Requires-Dist: sageodata-db >=0.19
Requires-Dist: dew-gwdata >=0.105
